ndg_chatbot_package/__init__.py
ndg_chatbot_package/tools/__init__.py
ndg_chatbot_package/tools/ndg_llm_tool.py
ndg_chatbot_package/tools/utils.py
ndg_chatbot_package/yamls/ndg_llm_tool.yaml
tests/__init__.py
tests/test_ndg_llm_tool.py
ndg_chatbot_package-0.0.2.dist-info/METADATA
ndg_chatbot_package-0.0.2.dist-info/WHEEL
ndg_chatbot_package-0.0.2.dist-info/entry_points.txt
ndg_chatbot_package-0.0.2.dist-info/top_level.txt
ndg_chatbot_package-0.0.2.dist-info/RECORD
