Metadata-Version: 2.1
Name: ndg_chatbot_package
Version: 0.0.2
Summary: This is my tools package
